voice100_runtime/__init__.py
voice100_runtime/asr.py
voice100_runtime/audio.py
voice100_runtime/text.py
voice100_runtime/tts.py
voice100_runtime/vocoder.py
voice100_runtime-1.6.1.dist-info/LICENSE
voice100_runtime-1.6.1.dist-info/METADATA
voice100_runtime-1.6.1.dist-info/WHEEL
voice100_runtime-1.6.1.dist-info/RECORD
