Metadata-Version: 2.1
Name: voice100-runtime
Version: 1.6.1
Summary: Voice100 Runtime is a TTS/ASR sample app that uses ONNX Runtime, WORLD and Voice100 neural TTS/ASR models on Python. Inference of Voice100 is low cost as its models are tiny and only depend on CNN without recursion.
License: MIT
Author: Katsuya Iida
Author-email: katsuya.iida@gmail.com
Requires-Python: >=3.8.1,<4.0.0
Classifier: License :: OSI Approved :: MIT License
Classifier: Programming Language :: Python :: 3
Classifier: Programming Language :: Python :: 3.9
Classifier: Programming Language :: Python :: 3.10
Classifier: Programming Language :: Python :: 3.11
Provides-Extra: lang-en-phone
Requires-Dist: librosa (>=0)
Requires-Dist: numpy (>=1.23)
Requires-Dist: onnxruntime (>=1.14)
Requires-Dist: pyworld (>=0.3.2,<0.4.0)
